i8kgui/__init__.py
i8kgui-0.8.4.data/data/share/applications/i8kgui.desktop
i8kgui-0.8.4.data/data/share/icons/i8kgui_icon.png
i8kgui-0.8.4.data/data/share/polkit-1/actions/com.ubuntu.pkexec.i8kgui_thermal_control.policy
i8kgui-0.8.4.data/data/share/polkit-1/actions/com.ubuntu.pkexec.smbios-thermal-ctl.policy
i8kgui-0.8.4.data/scripts/i8kgui
i8kgui-0.8.4.data/scripts/i8kgui_thermal_control
i8kgui-0.8.4.dist-info/LICENSE
i8kgui-0.8.4.dist-info/METADATA
i8kgui-0.8.4.dist-info/WHEEL
i8kgui-0.8.4.dist-info/top_level.txt
i8kgui-0.8.4.dist-info/RECORD
