Metadata-Version: 2.1
Name: i8kgui
Version: 0.8.4
Summary: A Dell thermal management GUI to control fan speeds and monitor temperatures.
Home-page: https://github.com/razman786/i8kgui
Author: Raz
Author-email: razman786@users.noreply.github.com
License: GPL
License-File: LICENSE
Requires-Dist: PySide6
Requires-Dist: psutil
Requires-Dist: py-cpuinfo
